{"name":"globus.gridftp","version":"6.1.0","documentationLinks":["http:\/\/toolkit.globus.org\/toolkit\/docs\/6.0\/gridftp\/#gridftp"],"target":[{"id":201,"productId":426,"platform":"sl6","arch":"x86_64","repositoryURL":"sw\/production\/umd\/3\/sl6\/x86_64\/updates","gpgkey":null,"rpms":[],"apicallback":"http:\/\/admin-repo.egi.eu\/api\/report\/release\/xml?id=8829","status":1}],"capabilities":["File Transfer"],"currentState":"deployed","technologyProvider":"Globus","contact":"mattias.ellert@fysast.uu.se","technicalContact":"mattias.ellert@fysast.uu.se","description":"GridFTP provides high-performance and reliable data transport.\n","releaseDate":"2015-11-26 14:00:57","majorVersion":6,"minorVersion":1,"revisionVersion":0,"releaseNotes":"http:\/\/toolkit.globus.org\/toolkit\/docs\/6.0\/gridftp\/#gridftp","changeLog":"N\/A","repositoryURL":"sw\/production\/umd\/3","distributionType":"UMD","distributionVersion":"3.14.0","softwareConfigurationLink":""}