{"name":"emi.cream-sge","version":"2.0.0","documentationLinks":["https:\/\/twiki.cern.ch\/twiki\/bin\/view\/EMI\/EMI2Final#CREAM_SGE_module_v_2_0_0_task_23"],"target":[],"capabilities":[],"currentState":"deployed","technologyProvider":"European Middleware Initiative","contact":"cristina.aiftimiei@pd.infn.it","technicalContact":"cristina.aiftimiei@pd.infn.it","description":"CREAM SGE module","releaseDate":"2012-10-09 16:04:39","majorVersion":2,"minorVersion":0,"revisionVersion":0,"releaseNotes":"https:\/\/twiki.cern.ch\/twiki\/bin\/view\/EMI\/EMI2Final#CREAM_SGE_module_v_2_0_0_task_23","changeLog":"https:\/\/twiki.cern.ch\/twiki\/bin\/view\/EMI\/EMI2Final#CREAM_SGE_module_v_2_0_0_task_23","repositoryURL":"sw\/production\/umd\/2","distributionType":"UMD","distributionVersion":"2.2.0","softwareConfigurationLink":""}