{"name":"ige.globus-default-security","version":"5.2.2","documentationLinks":[],"target":[],"capabilities":[],"currentState":"deployed","technologyProvider":"Initiative for Globus in Europe","contact":"mattias.ellert@fysast.uu.se","technicalContact":"mattias.ellert@fysast.uu.se","description":"The Grid Security Infrastructure (GSI) from the Globus Toolkit","releaseDate":"2013-02-18 12:33:41","majorVersion":5,"minorVersion":2,"revisionVersion":2,"releaseNotes":"Release notes are available from http:\/\/globus.org.eu\/toolkit\/docs\/5.2\/5.2.2\/gsic\/rn\/","changeLog":"Based on Globus Toolkit 5.2.2","repositoryURL":"sw\/production\/umd\/2","distributionType":"UMD","distributionVersion":"2.4.0","softwareConfigurationLink":""}