{"name":"gfal2.gfal2","version":"2.15.4","documentationLinks":["https:\/\/svnweb.cern.ch\/trac\/lcgutil\/wiki\/gfal2"],"target":[],"capabilities":["Client Tools"],"currentState":"deployed","technologyProvider":"Gfal2","contact":"dmc-support@cern.ch","technicalContact":"dmc-support@cern.ch","description":"GFAL (Grid File Access Library ) is a C library providing an abstraction layer of the grid storage system complexity.\n","releaseDate":"2018-07-11 11:42:33","majorVersion":2,"minorVersion":15,"revisionVersion":4,"releaseNotes":"https:\/\/dmc.web.cern.ch\/release\/gfal2-2154","changeLog":"https:\/\/dmc.web.cern.ch\/release\/gfal2-2154","repositoryURL":"sw\/production\/umd\/4","distributionType":"UMD","distributionVersion":"4.7.0","softwareConfigurationLink":""}