{"name":"emi.apel","version":"1.2.2","documentationLinks":["https:\/\/twiki.cern.ch\/twiki\/pub\/EMI\/EMI3APELClient\/APEL_Client_Functional_Description.pdf"],"target":[],"capabilities":["Accounting"],"currentState":"deployed","technologyProvider":"European Middleware Initiative","contact":"cristina.aiftimiei@pd.infn.it","technicalContact":"cristina.aiftimiei@pd.infn.it","description":"APEL (Accounting Processor for Event Logs) is a tool that gathers CPU accounting information by parsing batch system and blah accounting log files and inserts it into a local MySQL database. APEL then publishes the data into a centralised repository.","releaseDate":"2014-11-10 16:24:35","majorVersion":1,"minorVersion":2,"revisionVersion":2,"releaseNotes":"https:\/\/github.com\/apel\/apel\/blob\/1.2.2-1\/CHANGELOG","changeLog":"https:\/\/github.com\/apel\/apel\/blob\/1.2.2-1\/CHANGELOG","repositoryURL":"sw\/production\/umd\/3","distributionType":"UMD","distributionVersion":"3.9.0","softwareConfigurationLink":""}